agentrylab/__init__.py
agentrylab/__main__.py
agentrylab/api.py
agentrylab/lab.py
agentrylab/logging.py
agentrylab/settings.py
agentrylab/types.py
agentrylab/version.py
agentrylab/cli/__init__.py
agentrylab/cli/app.py
agentrylab/cli/commands/__init__.py
agentrylab/config/__init__.py
agentrylab/config/loader.py
agentrylab/config/validate.py
agentrylab/persistence/__init__.py
agentrylab/persistence/store.py
agentrylab/persistence/checkpoints/__init__.py
agentrylab/persistence/checkpoints/sqlite.py
agentrylab/persistence/transcript/__init__.py
agentrylab/persistence/transcript/jsonl.py
agentrylab/presets/__init__.py
agentrylab/presets/debates.yaml
agentrylab/presets/marketplace_deals.yaml
agentrylab/presets/research.yaml
agentrylab/presets/research_assistant.yaml
agentrylab/presets/standup_club.yaml
agentrylab/runtime/__init__.py
agentrylab/runtime/actions.py
agentrylab/runtime/engine.py
agentrylab/runtime/state.py
agentrylab/runtime/nodes/__init__.py
agentrylab/runtime/nodes/advisor.py
agentrylab/runtime/nodes/agent.py
agentrylab/runtime/nodes/base.py
agentrylab/runtime/nodes/factory.py
agentrylab/runtime/nodes/moderator.py
agentrylab/runtime/nodes/summarizer.py
agentrylab/runtime/nodes/user.py
agentrylab/runtime/providers/__init__.py
agentrylab/runtime/providers/base.py
agentrylab/runtime/providers/ollama.py
agentrylab/runtime/providers/openai.py
agentrylab/runtime/schedulers/__init__.py
agentrylab/runtime/schedulers/base.py
agentrylab/runtime/schedulers/every_n.py
agentrylab/runtime/schedulers/round_robin.py
agentrylab/runtime/tools/__init__.py
agentrylab/runtime/tools/apify_marketplace.py
agentrylab/runtime/tools/base.py
agentrylab/runtime/tools/ddg.py
agentrylab/runtime/tools/wolfram.py
agentrylab/telegram/__init__.py
agentrylab/telegram/adapter.py
agentrylab/telegram/exceptions.py
agentrylab/telegram/models.py
agentrylab/utils/__init__.py
agentrylab/utils/urls.py
agentrylab-0.2.0.dist-info/licenses/LICENSE
agentrylab-0.2.0.dist-info/METADATA
agentrylab-0.2.0.dist-info/WHEEL
agentrylab-0.2.0.dist-info/entry_points.txt
agentrylab-0.2.0.dist-info/top_level.txt
agentrylab-0.2.0.dist-info/RECORD
