Metadata-Version: 2.4
Name: agentrylab
Version: 0.2.0
Summary: Lightweight, hackable multi-agent orchestration lab (CLI + Python) with transcripts, checkpoints, budgets, and pluggable providers/tools.
Author: Alexey Kislitsin
License-Expression: MIT
Project-URL: Homepage, https://github.com/Alexeyisme/agentrylab
Project-URL: Repository, https://github.com/Alexeyisme/agentrylab
Project-URL: Documentation, https://github.com/Alexeyisme/agentrylab/tree/main/src/agentrylab/docs
Project-URL: Issues, https://github.com/Alexeyisme/agentrylab/issues
Keywords: multi-agent,llm,ai-agents,agent-orchestration,python,yaml-config,cli-tool,research,experimentation,ai-development,openai,ollama,llama3,transcripts,checkpoints,streaming,hackable,lightweight,lab,workflow-engine
Classifier: Development Status :: 3 - Alpha
Classifier: Intended Audience :: Developers
Classifier: Programming Language :: Python
Classifier: Programming Language :: Python :: 3
Classifier: Programming Language :: Python :: 3 :: Only
Classifier: Programming Language :: Python :: 3.11
Classifier: Programming Language :: Python :: 3.12
Classifier: Topic :: Software Development :: Libraries
Classifier: Topic :: Scientific/Engineering :: Artificial Intelligence
Requires-Python: >=3.11
License-File: LICENSE
Requires-Dist: pydantic>=2.7
Requires-Dist: pyyaml>=6.0.1
Requires-Dist: httpx>=0.27.0
Requires-Dist: jsonschema>=4.22.0
Requires-Dist: typer>=0.12.3
Requires-Dist: rich>=13.7.1
Requires-Dist: ddgs>=1.8.0
Requires-Dist: wolframalpha>=5.0.0
Requires-Dist: python-dotenv>=1.0.1
Provides-Extra: dev
Requires-Dist: pytest>=8.3.2; extra == "dev"
Requires-Dist: pytest-asyncio>=0.24.0; extra == "dev"
Requires-Dist: pytest-cov>=5.0.0; extra == "dev"
Requires-Dist: mypy>=1.11.1; extra == "dev"
Requires-Dist: ruff>=0.6.9; extra == "dev"
Requires-Dist: pyright>=1.1.381; extra == "dev"
Requires-Dist: types-PyYAML>=6.0.12.20240808; extra == "dev"
Requires-Dist: types-jsonschema>=4.23.0.20240813; extra == "dev"
Dynamic: license-file
